excel_runner/__init__.py
excel_runner/runner.py
excel_runner/lib/__init__.py
excel_runner/lib/a.txt
excel_runner/lib/calc.py
excel_runner-0.1.1.dist-info/METADATA
excel_runner-0.1.1.dist-info/WHEEL
excel_runner-0.1.1.dist-info/top_level.txt
excel_runner-0.1.1.dist-info/RECORD
