Metadata-Version: 2.1
Name: excel-runner
Version: 0.1.1
Home-page: http://github.com/hanzhichao/excel-runner
Author: Han ZhiChao
Author-email: superhin@126.com
License: MIT
Requires-Dist: requests
